[
  {
    "id": "6a5011a1-fe1f-47df-9a32-b5346b289391",
    "reservePrice": 0,
    "seller": "bob",
    "winner": null,
    "soldAmount": 0,
    "currentHighBid": 0,
    "createdAt": "2023-08-22T20:52:28.033955Z",
    "updatedAt": "2023-08-22T20:52:28.033955Z",
    "auctionEnd": "2023-09-10T20:52:28.033955Z",
    "status": "Live",
    "make": "Audi",
    "model": "R8",
    "year": 2021,
    "color": "White",
    "mileage": 10050,
    "imageUrl": "https://cdn.pixabay.com/photo/2019/12/26/20/50/audi-r8-4721217_960_720.jpg"
  },
  {
    "id": "40490065-dac7-46b6-acc4-df507e0d6570",
    "reservePrice": 20000,
    "seller": "tom",
    "winner": null,
    "soldAmount": 0,
    "currentHighBid": 0,
    "createdAt": "2023-08-22T20:52:28.033955Z",
    "updatedAt": "2023-08-22T20:52:28.033955Z",
    "auctionEnd": "2023-09-11T20:52:28.033955Z",
    "status": "Live",
    "make": "Audi",
    "model": "TT",
    "year": 2020,
    "color": "Black",
    "mileage": 25400,
    "imageUrl": "https://cdn.pixabay.com/photo/2016/09/01/15/06/audi-1636320_960_720.jpg"
  },
  {
    "id": "466e4744-4dc5-4987-aae0-b621acfc5e39",
    "reservePrice": 20000,
    "seller": "alice",
    "winner": null,
    "soldAmount": 0,
    "currentHighBid": 0,
    "createdAt": "2023-08-22T20:52:28.033954Z",
    "updatedAt": "2023-08-22T20:52:28.033954Z",
    "auctionEnd": "2023-09-21T20:52:28.033954Z",
    "status": "Live",
    "make": "BMW",
    "model": "X1",
    "year": 2017,
    "color": "White",
    "mileage": 90000,
    "imageUrl": "https://cdn.pixabay.com/photo/2017/08/31/05/47/bmw-2699538_960_720.jpg"
  },
  {
    "id": "c8c3ec17-01bf-49db-82aa-1ef80b833a9f",
    "reservePrice": 90000,
    "seller": "alice",
    "winner": null,
    "soldAmount": 0,
    "currentHighBid": 0,
    "createdAt": "2023-08-22T20:52:28.033953Z",
    "updatedAt": "2023-08-22T20:52:28.033953Z",
    "auctionEnd": "2023-10-21T20:52:28.033953Z",
    "status": "Live",
    "make": "Bugatti",
    "model": "Veyron",
    "year": 2018,
    "color": "Black",
    "mileage": 15035,
    "imageUrl": "https://cdn.pixabay.com/photo/2012/05/29/00/43/car-49278_960_720.jpg"
  },
  {
    "id": "dc1e4071-d19d-459b-b848-b5c3cd3d151f",
    "reservePrice": 20000,
    "seller": "bob",
    "winner": null,
    "soldAmount": 0,
    "currentHighBid": 0,
    "createdAt": "2023-08-22T20:52:28.033955Z",
    "updatedAt": "2023-08-22T20:52:28.033955Z",
    "auctionEnd": "2023-10-06T20:52:28.033955Z",
    "status": "Live",
    "make": "Ferrari",
    "model": "Spider",
    "year": 2015,
    "color": "Red",
    "mileage": 50000,
    "imageUrl": "https://cdn.pixabay.com/photo/2017/11/09/01/49/ferrari-458-spider-2932191_960_720.jpg"
  },
  {
    "id": "47111973-d176-4feb-848d-0ea22641c31a",
    "reservePrice": 150000,
    "seller": "alice",
    "winner": null,
    "soldAmount": 0,
    "currentHighBid": 0,
    "createdAt": "2023-08-22T20:52:28.033955Z",
    "updatedAt": "2023-08-22T20:52:28.033955Z",
    "auctionEnd": "2023-09-04T20:52:28.033955Z",
    "status": "Live",
    "make": "Ferrari",
    "model": "F-430",
    "year": 2022,
    "color": "Red",
    "mileage": 5000,
    "imageUrl": "https://cdn.pixabay.com/photo/2017/11/08/14/39/ferrari-f430-2930661_960_720.jpg"
  },
  {
    "id": "dde9cd71-9a9f-4f48-803d-4abe393be212",
    "reservePrice": 0,
    "seller": "test",
    "winner": null,
    "soldAmount": 0,
    "currentHighBid": 0,
    "createdAt": "2023-09-14T14:30:43.442062Z",
    "updatedAt": "2023-09-14T14:30:43.442063Z",
    "auctionEnd": "2023-09-28T14:30:43.423Z",
    "status": "Live",
    "make": "Ford",
    "model": "Escort",
    "year": 2021,
    "color": "White",
    "mileage": 10000,
    "imageUrl": "https://cdn.pixabay.com/photo/2018/02/04/15/45/car-3130111_960_720.jpg"
  },
  {
    "id": "2fca40cc-5125-4cda-9617-3087e23bb6ba",
    "reservePrice": 0,
    "seller": "test",
    "winner": null,
    "soldAmount": 0,
    "currentHighBid": 0,
    "createdAt": "2023-09-14T14:32:33.288762Z",
    "updatedAt": "2023-09-14T14:32:33.288762Z",
    "auctionEnd": "2023-09-28T14:32:33.129Z",
    "status": "Live",
    "make": "Ford",
    "model": "Escort",
    "year": 2021,
    "color": "White",
    "mileage": 10000,
    "imageUrl": "https://cdn.pixabay.com/photo/2018/02/04/15/45/car-3130111_960_720.jpg"
  },
  {
    "id": "911f1b93-5a08-4e17-9096-2f0b096fde3d",
    "reservePrice": 0,
    "seller": "test",
    "winner": null,
    "soldAmount": 0,
    "currentHighBid": 0,
    "createdAt": "2023-09-14T14:33:43.598065Z",
    "updatedAt": "2023-09-14T14:33:43.598065Z",
    "auctionEnd": "2023-09-28T14:33:43.451Z",
    "status": "Live",
    "make": "Ford",
    "model": "Escort",
    "year": 2021,
    "color": "White",
    "mileage": 10000,
    "imageUrl": "https://cdn.pixabay.com/photo/2018/02/04/15/45/car-3130111_960_720.jpg"
  },
  {
    "id": "3fb2074b-1b60-4003-bf67-1b1f94268aca",
    "reservePrice": 0,
    "seller": "test",
    "winner": null,
    "soldAmount": 0,
    "currentHighBid": 0,
    "createdAt": "2023-09-14T14:35:09.683732Z",
    "updatedAt": "2023-09-14T14:35:09.683733Z",
    "auctionEnd": "2023-09-28T14:35:09.639Z",
    "status": "Live",
    "make": "Ford",
    "model": "Escort",
    "year": 2021,
    "color": "White",
    "mileage": 10000,
    "imageUrl": "https://cdn.pixabay.com/photo/2018/02/04/15/45/car-3130111_960_720.jpg"
  },
  {
    "id": "93c815e3-7e32-4c1a-8047-57fda1e6be20",
    "reservePrice": 100,
    "seller": "test",
    "winner": null,
    "soldAmount": 0,
    "currentHighBid": 0,
    "createdAt": "2023-09-14T14:38:14.831429Z",
    "updatedAt": "2023-09-14T14:38:14.831429Z",
    "auctionEnd": "2023-09-28T14:38:14.695Z",
    "status": "Live",
    "make": "Ford",
    "model": "Escort",
    "year": 2021,
    "color": "White",
    "mileage": 10000,
    "imageUrl": "https://cdn.pixabay.com/photo/2018/02/04/15/45/car-3130111_960_720.jpg"
  },
  {
    "id": "37822ff7-6bad-48c7-b35c-419939368dd5",
    "reservePrice": 0,
    "seller": "test",
    "winner": null,
    "soldAmount": 0,
    "currentHighBid": 0,
    "createdAt": "2023-09-14T14:37:32.101673Z",
    "updatedAt": "2023-09-14T14:37:32.101673Z",
    "auctionEnd": "2023-09-28T14:37:32.058Z",
    "status": "Live",
    "make": "Ford",
    "model": "Escort",
    "year": 2021,
    "color": "White",
    "mileage": 10000,
    "imageUrl": "https://cdn.pixabay.com/photo/2018/02/04/15/45/car-3130111_960_720.jpg"
  },
  {
    "id": "3659ac24-29dd-407a-81f5-ecfe6f924b9b",
    "reservePrice": 20000,
    "seller": "bob",
    "winner": null,
    "soldAmount": 0,
    "currentHighBid": 0,
    "createdAt": "2023-08-22T20:52:28.033956Z",
    "updatedAt": "2023-08-22T20:52:28.033956Z",
    "auctionEnd": "2023-10-09T20:52:28.033956Z",
    "status": "Live",
    "make": "Ford",
    "model": "Model T",
    "year": 1938,
    "color": "Rust",
    "mileage": 150150,
    "imageUrl": "https://cdn.pixabay.com/photo/2017/08/02/19/47/vintage-2573090_960_720.jpg"
  },
  {
    "id": "afbee524-5972-4075-8800-7d1f9d7b0a0c",
    "reservePrice": 20000,
    "seller": "bob",
    "winner": null,
    "soldAmount": 0,
    "currentHighBid": 0,
    "createdAt": "2023-08-22T20:52:28.033729Z",
    "updatedAt": "2023-08-22T20:52:28.033729Z",
    "auctionEnd": "2023-09-01T20:52:28.033808Z",
    "status": "Live",
    "make": "Ford",
    "model": "GT",
    "year": 2020,
    "color": "White",
    "mileage": 50000,
    "imageUrl": "https://cdn.pixabay.com/photo/2016/05/06/16/32/car-1376190_960_720.jpg"
  },
  {
    "id": "bbab4d5a-8565-48b1-9450-5ac2a5c4a654",
    "reservePrice": 0,
    "seller": "bob",
    "winner": null,
    "soldAmount": 0,
    "currentHighBid": 0,
    "createdAt": "2023-08-22T20:52:28.033954Z",
    "updatedAt": "2023-08-22T20:52:28.033954Z",
    "auctionEnd": "2023-08-26T20:52:28.033954Z",
    "status": "Live",
    "make": "Ford",
    "model": "Mustang",
    "year": 2023,
    "color": "Black",
    "mileage": 65125,
    "imageUrl": "https://cdn.pixabay.com/photo/2012/11/02/13/02/car-63930_960_720.jpg"
  },
  {
    "id": "00aee0f7-6f06-4db7-8902-2d00a517e9b2",
    "reservePrice": 0,
    "seller": "test",
    "winner": null,
    "soldAmount": 0,
    "currentHighBid": 0,
    "createdAt": "2023-09-14T14:29:10.977615Z",
    "updatedAt": "2023-09-14T14:29:10.977615Z",
    "auctionEnd": "2023-09-28T14:29:10.796Z",
    "status": "Live",
    "make": "Ford",
    "model": "Escort",
    "year": 2021,
    "color": "White",
    "mileage": 10000,
    "imageUrl": "https://cdn.pixabay.com/photo/2018/02/04/15/45/car-3130111_960_720.jpg"
  },
  {
    "id": "a18afd8d-aa40-4215-889a-91378ff62cb4",
    "reservePrice": 0,
    "seller": "test",
    "winner": null,
    "soldAmount": 0,
    "currentHighBid": 0,
    "createdAt": "2023-09-14T14:30:41.947891Z",
    "updatedAt": "2023-09-14T14:30:41.947891Z",
    "auctionEnd": "2023-09-28T14:30:41.8Z",
    "status": "Live",
    "make": "Ford",
    "model": "Escort",
    "year": 2021,
    "color": "White",
    "mileage": 10000,
    "imageUrl": "https://cdn.pixabay.com/photo/2018/02/04/15/45/car-3130111_960_720.jpg"
  },
  {
    "id": "a444ea8f-bacd-4118-8662-17767469eb67",
    "reservePrice": 100,
    "seller": "test",
    "winner": null,
    "soldAmount": 0,
    "currentHighBid": 0,
    "createdAt": "2023-09-14T14:39:02.254124Z",
    "updatedAt": "2023-09-14T14:39:02.254124Z",
    "auctionEnd": "2023-09-28T14:39:02.207Z",
    "status": "Live",
    "make": "Ford Updated",
    "model": "Escort",
    "year": 2021,
    "color": "White",
    "mileage": 10000,
    "imageUrl": "https://cdn.pixabay.com/photo/2018/02/04/15/45/car-3130111_960_720.jpg"
  },
  {
    "id": "155225c1-4448-4066-9886-6786536e05ea",
    "reservePrice": 50000,
    "seller": "tom",
    "winner": null,
    "soldAmount": 0,
    "currentHighBid": 0,
    "createdAt": "2023-08-22T20:52:28.033954Z",
    "updatedAt": "2023-08-22T20:52:28.033954Z",
    "auctionEnd": "2023-08-12T20:52:28.033954Z",
    "status": "ReserveNotMet",
    "make": "Mercedes",
    "model": "SLK",
    "year": 2020,
    "color": "Silver",
    "mileage": 15001,
    "imageUrl": "https://cdn.pixabay.com/photo/2016/04/17/22/10/mercedes-benz-1335674_960_720.png"
  }
]
